pystyx/__init__.py
pystyx/__main__.py
pystyx/functions.py
pystyx/mapper.py
pystyx/parser.py
pystyx/postprocessor.py
pystyx/preprocessor.py
pystyx/processor.py
pystyx/shared.py
pystyx-0.8.5.dist-info/LICENSE
pystyx-0.8.5.dist-info/METADATA
pystyx-0.8.5.dist-info/WHEEL
pystyx-0.8.5.dist-info/top_level.txt
pystyx-0.8.5.dist-info/RECORD
