Metadata-Version: 2.1
Name: pystyx
Version: 0.8.5
Summary: Python Styx bindings for ETL/ELT declarative mapping syntax using TOML.
Home-page: https://github.com/styx-dev/pystyx
Author: Mark Keaton
Author-email: mkeaton@gmail.com
License: UNKNOWN
Platform: UNKNOWN
Classifier: Programming Language :: Python :: 3
Classifier: License :: OSI Approved :: MIT License
Classifier: Operating System :: OS Independent
